dup_crypto/__init__.py
dup_crypto/__test__.py
dup_crypto/libdup_crypto.so
dup_crypto-0.2.0.dist-info/LICENSE
dup_crypto-0.2.0.dist-info/METADATA
dup_crypto-0.2.0.dist-info/WHEEL
dup_crypto-0.2.0.dist-info/top_level.txt
dup_crypto-0.2.0.dist-info/RECORD
