Metadata-Version: 2.1
Name: dup-crypto
Version: 0.2.0
Summary: Duniter protocol cryptography
Home-page: https://git.duniter.org/tuxmain/dup-crypto-py
Author: Pascal Engélibert
Author-email: tuxmain@zettascript.org
License: UNKNOWN
Keywords: security cryptography
Platform: UNKNOWN
Classifier: Programming Language :: Python :: 3
Classifier: License :: OSI Approved :: GNU Affero General Public License v3
Classifier: Operating System :: OS Independent
Classifier: Topic :: Security :: Cryptography
Requires-Python: >=3.6
